langchain_milvus/__init__.py
langchain_milvus/function.py
langchain_milvus/py.typed
langchain_milvus/retrievers/__init__.py
langchain_milvus/retrievers/milvus_hybrid_search.py
langchain_milvus/retrievers/zilliz_cloud_pipeline_retriever.py
langchain_milvus/utils/__init__.py
langchain_milvus/utils/constant.py
langchain_milvus/utils/sparse.py
langchain_milvus/vectorstores/__init__.py
langchain_milvus/vectorstores/milvus.py
langchain_milvus/vectorstores/zilliz.py
langchain_milvus-0.3.2.dist-info/LICENSE
langchain_milvus-0.3.2.dist-info/METADATA
langchain_milvus-0.3.2.dist-info/WHEEL
langchain_milvus-0.3.2.dist-info/RECORD
